{"title":"[MyFirstSexTeacher.com / NaughtyAmerica.com] Taylor Wane","uid":6260161,"size":903890731,"categoryP":"porn","categoryS":"movies","magnet":"?xt=urn:btih:07cc1227e44e32a6090a13678fa5a2b6db95b510&amp;dn=%5BMyFirstSexTeacher.com+%2F+NaughtyAmerica.com%5D+Taylor+Wane+&amp;tr=udp%3A%2F%2Ftracker.openbittorrent.com%3A80&amp;tr=udp%3A%2F%2Fopen.demonii.com%3A1337&amp;tr=udp%3A%2F%2Ftracker.coppersurfer.tk%3A6969&amp;tr=udp%3A%2F%2Fexodus.desync.com%3A6969","seeders":1,"leechers":0,"uploader":"exmnova","files":1,"time":1300723018,"description":"[MyFirstSexTeacher.com / NaughtyAmerica.com] Taylor Wane \n &lt;a href=&quot;\nhttp://0.picswan.com/show.php/2526_1.jpg.html&quot; rel=&quot;nofollow&quot; target=&quot;_NEW&quot;&gt;\nhttp://0.picswan.com/show.php/2526_1.jpg.html&lt;/a&gt;\n &lt;a href=&quot;\nhttp://0.picswan.com/show.php/2525_2.jpg.html&quot; rel=&quot;nofollow&quot; target=&quot;_NEW&quot;&gt;\nhttp://0.picswan.com/show.php/2525_2.jpg.html&lt;/a&gt;\n","torrent":{"xt":"urn:btih:07cc1227e44e32a6090a13678fa5a2b6db95b510","amp;dn":"%5BMyFirstSexTeacher.com+%2F+NaughtyAmerica.com%5D+Taylor+Wane+","amp;tr":["udp%3A%2F%2Ftracker.openbittorrent.com%3A80","udp%3A%2F%2Fopen.demonii.com%3A1337","udp%3A%2F%2Ftracker.coppersurfer.tk%3A6969","udp%3A%2F%2Fexodus.desync.com%3A6969"],"infoHash":"07cc1227e44e32a6090a13678fa5a2b6db95b510","infoHashBuffer":{"type":"Buffer","data":[7,204,18,39,228,78,50,166,9,10,19,103,143,165,162,182,219,149,181,16]},"announce":[],"urlList":[]}}