{"title":"Batman Arkham Asylum [Spanish_ENG_FR_IT_GER][XBOX360][REGIONFREE","uid":5064236,"size":7267528807,"categoryP":"games","categoryS":"xbox360","magnet":"?xt=urn:btih:096a3152629685cf539cb215b82529beffaf6044&amp;dn=Batman+Arkham+Asylum+%5BSpanish_ENG_FR_IT_GER%5D%5BXBOX360%5D%5BREGIONFREE&amp;tr=udp%3A%2F%2Ftracker.openbittorrent.com%3A80&amp;tr=udp%3A%2F%2Fopen.demonii.com%3A1337&amp;tr=udp%3A%2F%2Ftracker.coppersurfer.tk%3A6969&amp;tr=udp%3A%2F%2Fexodus.desync.com%3A6969","seeders":1,"leechers":0,"uploader":"laurinha","files":-1,"time":1250851777,"description":"Ã‚Â¡El Caballero Oscuro se enfrenta a su mayor desafÃƒÂ­o cuando queda atrapado junto a sus mÃƒÂ¡s peligrosos enemigos en el manicomio de Gotham City, el Asilo Arkham! Batman: Arkham Asylum presenta una aventura ÃƒÂºnica, oscura y atmosfÃƒÂ©rica que nos transporta a los entresijos del hospital psiquiÃƒÂ¡trico de Gotham, donde estÃƒÂ¡n encerrados los delincuentes psicÃƒÂ³ticos. Con unos grÃƒÂ¡ficos espectaculares y una atmÃƒÂ³sfera variable que nos envuelve por completo, Batman: Arkham Asylum ofrece distintas opciones de juego que llevan al lÃƒÂ­mite todos los juegos de acciÃƒÂ³n, aventuras y superhÃƒÂ©roes.\n\n* SÃƒÂºpervillanos: enfrÃƒÂ©ntate a los lunÃƒÂ¡ticos mÃƒÂ¡s famosos de Gotham, incluido el Joker, Harley Quinn, Bane, Hiedra Venenosa y Killer Croc.\n* Arsenal de Batman: utiliza las habilidades investigadoras de Batman y la tecnologÃƒÂ­a forense mÃƒÂ¡s avanzada para recopilar pruebas y pistas.\n* Asesino silencioso: muÃƒÂ©vete en la sombra y atemoriza a tus enemigos.\n* Combate cuerpo a cuerpo: lanza combos brutales con el innovador sistema de combate FreeFlow.","torrent":{"xt":"urn:btih:096a3152629685cf539cb215b82529beffaf6044","amp;dn":"Batman+Arkham+Asylum+%5BSpanish_ENG_FR_IT_GER%5D%5BXBOX360%5D%5BREGIONFREE","amp;tr":["udp%3A%2F%2Ftracker.openbittorrent.com%3A80","udp%3A%2F%2Fopen.demonii.com%3A1337","udp%3A%2F%2Ftracker.coppersurfer.tk%3A6969","udp%3A%2F%2Fexodus.desync.com%3A6969"],"infoHash":"096a3152629685cf539cb215b82529beffaf6044","infoHashBuffer":{"type":"Buffer","data":[9,106,49,82,98,150,133,207,83,156,178,21,184,37,41,190,255,175,96,68]},"announce":[],"urlList":[]}}