{"title":"[Classic Sci-Fi ] Monster from Green Hell (1958) (by slowone).av","uid":5611148,"size":599145698,"categoryP":"video","categoryS":"movies","magnet":"?xt=urn:btih:0c776792101006bd91be72e6eefc5b14f81fb1dd&amp;dn=%5BClassic+Sci-Fi+%5D+Monster+from+Green+Hell+%281958%29+%28by+slowone%29.av&amp;tr=udp%3A%2F%2Ftracker.openbittorrent.com%3A80&amp;tr=udp%3A%2F%2Fopen.demonii.com%3A1337&amp;tr=udp%3A%2F%2Ftracker.coppersurfer.tk%3A6969&amp;tr=udp%3A%2F%2Fexodus.desync.com%3A6969","seeders":1,"leechers":0,"uploader":"bitstreeem","files":-1,"time":1275870995,"description":"Video quality = Average\n\n\nAtomic mutations with an appetite for flesh!\n\n &lt;a href=&quot;\nhttp://www.imdb.com/title/tt0050723/&quot; rel=&quot;nofollow&quot; target=&quot;_NEW&quot;&gt;\nhttp://www.imdb.com/title/tt0050723/&lt;/a&gt;\n\n\n &lt;a href=&quot;\thttp://thepiratebay.se/user/bitstreeem&quot; rel=&quot;nofollow&quot; target=&quot;_NEW&quot;&gt;\thttp://thepiratebay.se/user/bitstreeem&lt;/a&gt;","torrent":{"xt":"urn:btih:0c776792101006bd91be72e6eefc5b14f81fb1dd","amp;dn":"%5BClassic+Sci-Fi+%5D+Monster+from+Green+Hell+%281958%29+%28by+slowone%29.av","amp;tr":["udp%3A%2F%2Ftracker.openbittorrent.com%3A80","udp%3A%2F%2Fopen.demonii.com%3A1337","udp%3A%2F%2Ftracker.coppersurfer.tk%3A6969","udp%3A%2F%2Fexodus.desync.com%3A6969"],"infoHash":"0c776792101006bd91be72e6eefc5b14f81fb1dd","infoHashBuffer":{"type":"Buffer","data":[12,119,103,146,16,16,6,189,145,190,114,230,238,252,91,20,248,31,177,221]},"announce":[],"urlList":[]}}