{"title":"Samantha Who? Season 2","uid":5035162,"size":3668755120,"categoryP":"video","categoryS":"tv_shows","magnet":"?xt=urn:btih:1ada7dcdc9b2ec75cef6cf652b61a1c2188f455b&amp;dn=Samantha+Who%3F+Season+2&amp;tr=udp%3A%2F%2Ftracker.openbittorrent.com%3A80&amp;tr=udp%3A%2F%2Fopen.demonii.com%3A1337&amp;tr=udp%3A%2F%2Ftracker.coppersurfer.tk%3A6969&amp;tr=udp%3A%2F%2Fexodus.desync.com%3A6969","seeders":1,"leechers":3,"uploader":"redmannjr","files":20,"time":1249079958,"description":"this is all the high quality episodes dowloaded from here and saved as one upload\ndownload and seed please","torrent":{"xt":"urn:btih:1ada7dcdc9b2ec75cef6cf652b61a1c2188f455b","amp;dn":"Samantha+Who%3F+Season+2","amp;tr":["udp%3A%2F%2Ftracker.openbittorrent.com%3A80","udp%3A%2F%2Fopen.demonii.com%3A1337","udp%3A%2F%2Ftracker.coppersurfer.tk%3A6969","udp%3A%2F%2Fexodus.desync.com%3A6969"],"infoHash":"1ada7dcdc9b2ec75cef6cf652b61a1c2188f455b","infoHashBuffer":{"type":"Buffer","data":[26,218,125,205,201,178,236,117,206,246,207,101,43,97,161,194,24,143,69,91]},"announce":[],"urlList":[]}}