{"title":"Wikileaks - Inside Julian Assange's War on Secrecy (2011)","uid":6237225,"size":180736705,"categoryP":"audio","categoryS":"audio_books","magnet":"?xt=urn:btih:1c100f7e14b70d950322b803fc0193efcffd069d&amp;dn=Wikileaks+-+Inside+Julian+Assange%5C%27s+War+on+Secrecy+%282011%29&amp;tr=udp%3A%2F%2Ftracker.openbittorrent.com%3A80&amp;tr=udp%3A%2F%2Fopen.demonii.com%3A1337&amp;tr=udp%3A%2F%2Ftracker.coppersurfer.tk%3A6969&amp;tr=udp%3A%2F%2Fexodus.desync.com%3A6969","seeders":1,"leechers":0,"uploader":"WentloogWhix","files":1,"time":1299924232,"description":"Luke  Harding, David Leigh - Wikileaks - Inside Julian Assange's War on Secrecy (2011) Guardian press\n\nAudio book 13 hrs 3 mins unabridged.\n\nPlease be *very patient* with this download. I have limited bandwidth.","torrent":{"xt":"urn:btih:1c100f7e14b70d950322b803fc0193efcffd069d","amp;dn":"Wikileaks+-+Inside+Julian+Assange%5C%27s+War+on+Secrecy+%282011%29","amp;tr":["udp%3A%2F%2Ftracker.openbittorrent.com%3A80","udp%3A%2F%2Fopen.demonii.com%3A1337","udp%3A%2F%2Ftracker.coppersurfer.tk%3A6969","udp%3A%2F%2Fexodus.desync.com%3A6969"],"infoHash":"1c100f7e14b70d950322b803fc0193efcffd069d","infoHashBuffer":{"type":"Buffer","data":[28,16,15,126,20,183,13,149,3,34,184,3,252,1,147,239,207,253,6,157]},"announce":[],"urlList":[]}}