{"title":"Semi-Pro","uid":5003977,"size":733888512,"categoryP":"video","categoryS":"movies","magnet":"?xt=urn:btih:3ce8c1c832b7c95dd987ee11dc147524df2cc625&amp;dn=Semi-Pro&amp;tr=udp%3A%2F%2Ftracker.openbittorrent.com%3A80&amp;tr=udp%3A%2F%2Fopen.demonii.com%3A1337&amp;tr=udp%3A%2F%2Ftracker.coppersurfer.tk%3A6969&amp;tr=udp%3A%2F%2Fexodus.desync.com%3A6969","seeders":1,"leechers":0,"uploader":"LilHess","files":1,"time":1247649392,"description":"Semi Pro","torrent":{"xt":"urn:btih:3ce8c1c832b7c95dd987ee11dc147524df2cc625","amp;dn":"Semi-Pro","amp;tr":["udp%3A%2F%2Ftracker.openbittorrent.com%3A80","udp%3A%2F%2Fopen.demonii.com%3A1337","udp%3A%2F%2Ftracker.coppersurfer.tk%3A6969","udp%3A%2F%2Fexodus.desync.com%3A6969"],"infoHash":"3ce8c1c832b7c95dd987ee11dc147524df2cc625","infoHashBuffer":{"type":"Buffer","data":[60,232,193,200,50,183,201,93,217,135,238,17,220,20,117,36,223,44,198,37]},"announce":[],"urlList":[]}}