{"title":"Fate/stay night Complete Series (Dual Audio)","uid":5090068,"size":2088235770,"categoryP":"video","categoryS":"tv_shows","magnet":"?xt=urn:btih:401fa294b4ffc065b300e4b98d58daf55e7a8a6c&amp;dn=Fate%2Fstay+night+Complete+Series+%28Dual+Audio%29&amp;tr=udp%3A%2F%2Ftracker.openbittorrent.com%3A80&amp;tr=udp%3A%2F%2Fopen.demonii.com%3A1337&amp;tr=udp%3A%2F%2Ftracker.coppersurfer.tk%3A6969&amp;tr=udp%3A%2F%2Fexodus.desync.com%3A6969","seeders":1,"leechers":1,"uploader":"youssef0eddoumali","files":24,"time":1253064408,"description":"Yes Check Out My Other Uploads And Stay On The Seed Side","torrent":{"xt":"urn:btih:401fa294b4ffc065b300e4b98d58daf55e7a8a6c","amp;dn":"Fate%2Fstay+night+Complete+Series+%28Dual+Audio%29","amp;tr":["udp%3A%2F%2Ftracker.openbittorrent.com%3A80","udp%3A%2F%2Fopen.demonii.com%3A1337","udp%3A%2F%2Ftracker.coppersurfer.tk%3A6969","udp%3A%2F%2Fexodus.desync.com%3A6969"],"infoHash":"401fa294b4ffc065b300e4b98d58daf55e7a8a6c","infoHashBuffer":{"type":"Buffer","data":[64,31,162,148,180,255,192,101,179,0,228,185,141,88,218,245,94,122,138,108]},"announce":[],"urlList":[]}}