{"title":"Caro Emerald - Deleted Scenes From The Cutting Room Floor","uid":6134430,"size":126681144,"categoryP":"audio","categoryS":"music","magnet":"?xt=urn:btih:70aa7565e3e3bf0e656237c50bb93aec5b0b1257&amp;dn=Caro+Emerald+-+Deleted+Scenes+From+The+Cutting+Room+Floor&amp;tr=udp%3A%2F%2Ftracker.openbittorrent.com%3A80&amp;tr=udp%3A%2F%2Fopen.demonii.com%3A1337&amp;tr=udp%3A%2F%2Ftracker.coppersurfer.tk%3A6969&amp;tr=udp%3A%2F%2Fexodus.desync.com%3A6969","seeders":1,"leechers":1,"uploader":null,"files":14,"time":1296245040,"description":"Caro Emerald - Deleted Scenes From The Cutting Room Floor (2010)\n\n\nBeschrijving:\n\nIn 2007 werd Caro gebeld door producers David Schreurs en Jan van Wieringen. Zij hadden met Vince Degiorgio (o.a. N Sync, Atomic Kitten) een liedje geschreven voor een Japanse act, of Caro de demo in kon zingen. Hoewel het iedereen gelijk opviel hoe goed het liedje bij Caro's stem paste belandde &quot;Back It Up&quot; op de plank bij een aantal muziek uitgevers.\n\nEen jaar later kreeg Caro de kans om het liedje live te zingen op AT5. Het sloeg direct aan: kijkers bleven maar bellen en mailen, wie die zanger...\n\nInfo:\n\nTracklist\n1. That Man\n2. Just One Dance\n3. Riviera Life\n4. Back It Up\n5. The Other Woman\n6. Absolutely Me\n7. You Don't Love Me\n8. Dr. Wanna Do\n9. Stuck\n10. I Know That He's Mine\n11. A Night Like This\n12. The Lipstick On His Collar\n\n\nFormaat : mp3\n\n","torrent":{"xt":"urn:btih:70aa7565e3e3bf0e656237c50bb93aec5b0b1257","amp;dn":"Caro+Emerald+-+Deleted+Scenes+From+The+Cutting+Room+Floor","amp;tr":["udp%3A%2F%2Ftracker.openbittorrent.com%3A80","udp%3A%2F%2Fopen.demonii.com%3A1337","udp%3A%2F%2Ftracker.coppersurfer.tk%3A6969","udp%3A%2F%2Fexodus.desync.com%3A6969"],"infoHash":"70aa7565e3e3bf0e656237c50bb93aec5b0b1257","infoHashBuffer":{"type":"Buffer","data":[112,170,117,101,227,227,191,14,101,98,55,197,11,185,58,236,91,11,18,87]},"announce":[],"urlList":[]}}