{"title":"[DPFanatics.com / 21Sextury.com] Lexy Little","uid":6237883,"size":400598891,"categoryP":"porn","categoryS":"movies","magnet":"?xt=urn:btih:79c20c3ad5e909e6f52dada59f8196ef9116494a&amp;dn=%5BDPFanatics.com+%2F+21Sextury.com%5D+Lexy+Little+&amp;tr=udp%3A%2F%2Ftracker.openbittorrent.com%3A80&amp;tr=udp%3A%2F%2Fopen.demonii.com%3A1337&amp;tr=udp%3A%2F%2Ftracker.coppersurfer.tk%3A6969&amp;tr=udp%3A%2F%2Fexodus.desync.com%3A6969","seeders":1,"leechers":0,"uploader":"exmnova","files":1,"time":1299943514,"description":"[DPFanatics.com / 21Sextury.com] Lexy Little \n &lt;a href=&quot;\nhttp://0.picswan.com/show.php/1195_1.jpg.html&quot; rel=&quot;nofollow&quot; target=&quot;_NEW&quot;&gt;\nhttp://0.picswan.com/show.php/1195_1.jpg.html&lt;/a&gt;\n &lt;a href=&quot;\nhttp://0.picswan.com/show.php/1194_2.jpg.html&quot; rel=&quot;nofollow&quot; target=&quot;_NEW&quot;&gt;\nhttp://0.picswan.com/show.php/1194_2.jpg.html&lt;/a&gt;\n","torrent":{"xt":"urn:btih:79c20c3ad5e909e6f52dada59f8196ef9116494a","amp;dn":"%5BDPFanatics.com+%2F+21Sextury.com%5D+Lexy+Little+","amp;tr":["udp%3A%2F%2Ftracker.openbittorrent.com%3A80","udp%3A%2F%2Fopen.demonii.com%3A1337","udp%3A%2F%2Ftracker.coppersurfer.tk%3A6969","udp%3A%2F%2Fexodus.desync.com%3A6969"],"infoHash":"79c20c3ad5e909e6f52dada59f8196ef9116494a","infoHashBuffer":{"type":"Buffer","data":[121,194,12,58,213,233,9,230,245,45,173,165,159,129,150,239,145,22,73,74]},"announce":[],"urlList":[]}}