{"title":"Chinesetorrent","uid":6308388,"size":11338017076,"categoryP":"other","categoryS":"other","magnet":"?xt=urn:btih:7b03803e0d1cbc755e9977ee26bd73dffd1b67be&amp;dn=Chinesetorrent&amp;tr=udp%3A%2F%2Ftracker.openbittorrent.com%3A80&amp;tr=udp%3A%2F%2Fopen.demonii.com%3A1337&amp;tr=udp%3A%2F%2Ftracker.coppersurfer.tk%3A6969&amp;tr=udp%3A%2F%2Fexodus.desync.com%3A6969","seeders":1,"leechers":2,"uploader":null,"files":1741,"time":1302395366,"description":"My complete Chinese learning experience!\n\n\n3000 common.doc\nA Dictionary of Chinese Characters Accessed by Phonetics.pdf\nAdvanced Chinese.pdf\nchinese 8000.xls\nChinese Characters.pdf\nChinesePod Advanced\nChinesePod Basic\nChinesePod Elementary\nChinesePod Intermediate\nChinesePod Upper Intermediate\nComprehensive Grammar Chinese.pdf\ndir\ndir.txt\nElementary Chinese.pdf\nFun_with_Chinese_Characters_v.1.pdf\nFun_with_Chinese_Characters_v.2.pdf\nFun_with_Chinese_Characters_v.3.pdf\nIntermediate Chinese.pdf\nNPCR textbook 1.pdf\nPimsleurMandarinChinese I Transcript.pdf\nPimsleurMandarinChineseIITranscript.pdf\nradical.doc\nRC_Conversations_v1.02.pdf\nRemembering Simplified Hanzi.pdf\n\nEnjoy!","torrent":{"xt":"urn:btih:7b03803e0d1cbc755e9977ee26bd73dffd1b67be","amp;dn":"Chinesetorrent","amp;tr":["udp%3A%2F%2Ftracker.openbittorrent.com%3A80","udp%3A%2F%2Fopen.demonii.com%3A1337","udp%3A%2F%2Ftracker.coppersurfer.tk%3A6969","udp%3A%2F%2Fexodus.desync.com%3A6969"],"infoHash":"7b03803e0d1cbc755e9977ee26bd73dffd1b67be","infoHashBuffer":{"type":"Buffer","data":[123,3,128,62,13,28,188,117,94,153,119,238,38,189,115,223,253,27,103,190]},"announce":[],"urlList":[]}}