{"title":"Sim City Societies [MULTI5]","uid":5028798,"size":1778243982,"categoryP":"games","categoryS":"pc","magnet":"?xt=urn:btih:7cdcc1ed792d40e25d3786ddfc5863a22b0b84e8&amp;dn=Sim+City+Societies+%5BMULTI5%5D&amp;tr=udp%3A%2F%2Ftracker.openbittorrent.com%3A80&amp;tr=udp%3A%2F%2Fopen.demonii.com%3A1337&amp;tr=udp%3A%2F%2Ftracker.coppersurfer.tk%3A6969&amp;tr=udp%3A%2F%2Fexodus.desync.com%3A6969","seeders":1,"leechers":0,"uploader":"thenoobish","files":38,"time":1248818173,"description":"\nPlataforma: PC\nIdioma: EspaÃƒÂ±ol,English,French,Italian,German\nGenero:Estrategia\nCalidad: DVD\nFormato: ISO\nTamaÃƒÂ±o: 1.66 GB\nFecha: 17-11-2007\nUploader: TXT\nVer Trailer\nFichero: DESCARGAR TORRENT\n\nCompra CDs/DVDs al mejor precio AquÃƒÂ­\nDescripcion:\n\nLa nueva entrega de la saga SimCity, conocida como SimCity Societies, lleva un paso mÃƒÂ¡s allÃƒÂ¡ este simulador urbanÃƒÂ­stico con la introducciÃƒÂ³n de diferentes ÃƒÂ©pocas histÃƒÂ³ricas.\n\nEn Societies cobrarÃƒÂ¡ gran importancia no solo la planificaciÃƒÂ³n de nuestra ciudad, sino las sociedades a las que demos lugar como resultado de esto. Podremos crear de este modo una sociedad bohemia, o un represor estado policial al estilo de 1984. La decisiÃƒÂ³n es completamente nuestra.","torrent":{"xt":"urn:btih:7cdcc1ed792d40e25d3786ddfc5863a22b0b84e8","amp;dn":"Sim+City+Societies+%5BMULTI5%5D","amp;tr":["udp%3A%2F%2Ftracker.openbittorrent.com%3A80","udp%3A%2F%2Fopen.demonii.com%3A1337","udp%3A%2F%2Ftracker.coppersurfer.tk%3A6969","udp%3A%2F%2Fexodus.desync.com%3A6969"],"infoHash":"7cdcc1ed792d40e25d3786ddfc5863a22b0b84e8","infoHashBuffer":{"type":"Buffer","data":[124,220,193,237,121,45,64,226,93,55,134,221,252,88,99,162,43,11,132,232]},"announce":[],"urlList":[]}}