{"title":"Kid Cudi A Kid Named Cudi Read - 2009(split tracks + cover)barne","uid":5084604,"size":60837864,"categoryP":"audio","categoryS":"music","magnet":"?xt=urn:btih:7d2915e4967d3bf8bec41a346e3517dd9f2acf8d&amp;dn=Kid+Cudi+A+Kid+Named+Cudi+Read+-+2009%28split+tracks+%2B+cover%29barne&amp;tr=udp%3A%2F%2Ftracker.openbittorrent.com%3A80&amp;tr=udp%3A%2F%2Fopen.demonii.com%3A1337&amp;tr=udp%3A%2F%2Ftracker.coppersurfer.tk%3A6969&amp;tr=udp%3A%2F%2Fexodus.desync.com%3A6969","seeders":1,"leechers":0,"uploader":"michelinman","files":19,"time":1252614505,"description":"[img]http://ecx.images-amazon.com/images/I/41BqlukA0fL.jpg[/img]\n\nARTiST:...Kid Cudi\nALBUM:....A Kid Named Cudi\nSOURCE:.......CDDA\nLABEL:........Groove Attack GRABBER:.....EAC\nRELEASEDATE:..Sep-01-2009 ENCODER:.....Lame 3.97\nSTREETDATE:...Sep-07-2009 TRACKS:......17\nGENRE:........Hip-Hop PLAYTiME:....50:13 min\nURL:..........www.kidcudi.com SiZE:........57,9 MB\nRELEASETYPE:..Album LANGUAGE:....English\nQUALiTY: VBRkbps / 44,1kHz / Joint-Stereo\n01. Intro [00:52]\n02. Down &amp; Out [04:11]\n03. Is There Any Love? feat. Wale [03:33]\n04. Cudi Get [02:22]\n05. Man On The Moon (The Anthem) [03:29]\n06. The Prayer [03:41]\n07. Day N Nite [02:50]\n08. Embrace The Martian feat. Crookers [03:37]\n09. Maui Wowie [02:26]\n10. 50 Ways To Make A Record [02:57]\n11. Whenever [02:06]\n12. Pillow Talk [03:26]\n13. Save My Soul (The Cudi Confession) [02:05]\n14. T.G.I.F. feat. Chip The Ripper [02:25]\n15. Cudi Spazzin [03:08]\n16. Cleveland Is The Reason [03:48]\n17. Heaven At Nite [03:17]\n\n[img]http://i78.photobucket.com/albums/j81/wrcfoucs/watching3vemq8.gif[/img]\n\n[img]http://i121.photobucket.com/albums/o219/uuffoo/vghlr7.png[/img]\n\n","torrent":{"xt":"urn:btih:7d2915e4967d3bf8bec41a346e3517dd9f2acf8d","amp;dn":"Kid+Cudi+A+Kid+Named+Cudi+Read+-+2009%28split+tracks+%2B+cover%29barne","amp;tr":["udp%3A%2F%2Ftracker.openbittorrent.com%3A80","udp%3A%2F%2Fopen.demonii.com%3A1337","udp%3A%2F%2Ftracker.coppersurfer.tk%3A6969","udp%3A%2F%2Fexodus.desync.com%3A6969"],"infoHash":"7d2915e4967d3bf8bec41a346e3517dd9f2acf8d","infoHashBuffer":{"type":"Buffer","data":[125,41,21,228,150,125,59,248,190,196,26,52,110,53,23,221,159,42,207,141]},"announce":[],"urlList":[]}}