{"title":"Skyline.2010.FRENCH.BDRiP.XViD-THENiGHTMARE","uid":6246934,"size":734019584,"categoryP":"video","categoryS":"movies","magnet":"?xt=urn:btih:ac60f0eb5c5561df4e8dd61a4bc5110a7dd4c73e&amp;dn=Skyline.2010.FRENCH.BDRiP.XViD-THENiGHTMARE&amp;tr=udp%3A%2F%2Ftracker.openbittorrent.com%3A80&amp;tr=udp%3A%2F%2Fopen.demonii.com%3A1337&amp;tr=udp%3A%2F%2Ftracker.coppersurfer.tk%3A6969&amp;tr=udp%3A%2F%2Fexodus.desync.com%3A6969","seeders":1,"leechers":0,"uploader":"Bensoussa","files":1,"time":1300269479,"description":"RÃƒÂ©alisateur : Colin Strause\nActeurs : Eric Balfour, Scottie Thompson, David Zayas\nGenre : Science fiction\nDurÃƒÂ©e : 01h33\nDate de sortie : 15 dÃƒÂ©cembre 2010\nAnnÃƒÂ©e de production : 2010\nTitre Original : Skyline\n\n\nAprÃƒÂ¨s une soirÃƒÂ©e bien arrosÃƒÂ©e, un groupe d'amis est rÃƒÂ©veillÃƒÂ© par d'ÃƒÂ©tranges lumiÃƒÂ¨res dans le ciel. Ils dÃƒÂ©couvrent avec horreur de gigantesques vaisseaux extraterrestres surplombant les mÃƒÂ©tropoles du monde entier. De puissantes sources lumineuses semblent aspirer les hommes par milliers... La stupeur passÃƒÂ©e, la fuite et la rÃƒÂ©sistance s'organisent. L'humanitÃƒÂ© est-elle condamnÃƒÂ©e ÃƒÂ  disparaÃƒÂ®tre ?\n\nQualitÃƒÂ© : DVDRiP\nFormat : XviD\nLangue : FranÃƒÂ§ais\nSous-titres : Aucun\nDÃƒÂ©coupÃƒÂ© avec : Aucun\nNombre de fichiers : 1\nTaille des fichiers : 700 Mo\nTaille totale : 700 Mo","torrent":{"xt":"urn:btih:ac60f0eb5c5561df4e8dd61a4bc5110a7dd4c73e","amp;dn":"Skyline.2010.FRENCH.BDRiP.XViD-THENiGHTMARE","amp;tr":["udp%3A%2F%2Ftracker.openbittorrent.com%3A80","udp%3A%2F%2Fopen.demonii.com%3A1337","udp%3A%2F%2Ftracker.coppersurfer.tk%3A6969","udp%3A%2F%2Fexodus.desync.com%3A6969"],"infoHash":"ac60f0eb5c5561df4e8dd61a4bc5110a7dd4c73e","infoHashBuffer":{"type":"Buffer","data":[172,96,240,235,92,85,97,223,78,141,214,26,75,197,17,10,125,212,199,62]},"announce":[],"urlList":[]}}