{"title":"I, Tintin (Moi, Tintin) - 1976 Documentary","uid":5055174,"size":441303657,"categoryP":"video","categoryS":"tv_shows","magnet":"?xt=urn:btih:c007dee92b47b1fa446248d5536405ddc70a92d7&amp;dn=I%2C+Tintin+%28Moi%2C+Tintin%29+-+1976+Documentary&amp;tr=udp%3A%2F%2Ftracker.openbittorrent.com%3A80&amp;tr=udp%3A%2F%2Fopen.demonii.com%3A1337&amp;tr=udp%3A%2F%2Ftracker.coppersurfer.tk%3A6969&amp;tr=udp%3A%2F%2Fexodus.desync.com%3A6969","seeders":1,"leechers":0,"uploader":"eddie1969","files":2,"time":1250374266,"description":"TV : Documentary : VHS quality : English\n\n\nRunning Time: Approx. 52minutes.\n\n\n\nThis is a Belgian TV documentary on Tintin based on GÃƒÂ©rard Valet's interview with HergÃƒÂ©. It has some remarkable footage of Herge's reunion with his old friend Chang (from The Blue Lotus and Tintin in Tibet) at the airport in Brussels.\n\nAlthough it was originally in French, here is a great chance to see it with English narration (and English subtitles when necessary) from Australian television.\n\nAlthough this documentary originally dates from 1976, I think it was redone a bit (added footage, etc.) in the early 1990's - if anyone knows the story there, please explain in the comments.\n\nThe quality is not pristine, but all things considered it is very watchable considering it's age and rarity.\n\n\n\nEnjoy and Seed!!","torrent":{"xt":"urn:btih:c007dee92b47b1fa446248d5536405ddc70a92d7","amp;dn":"I%2C+Tintin+%28Moi%2C+Tintin%29+-+1976+Documentary","amp;tr":["udp%3A%2F%2Ftracker.openbittorrent.com%3A80","udp%3A%2F%2Fopen.demonii.com%3A1337","udp%3A%2F%2Ftracker.coppersurfer.tk%3A6969","udp%3A%2F%2Fexodus.desync.com%3A6969"],"infoHash":"c007dee92b47b1fa446248d5536405ddc70a92d7","infoHashBuffer":{"type":"Buffer","data":[192,7,222,233,43,71,177,250,68,98,72,213,83,100,5,221,199,10,146,215]},"announce":[],"urlList":[]}}