{"title":"(Various)  Fabulous Fifties (3CD)","uid":5104023,"size":201477177,"categoryP":"audio","categoryS":"music","magnet":"?xt=urn:btih:c09751b88d74b35c0a8ce99313d1d337f65e2298&amp;dn=%28Various%29++Fabulous+Fifties+%283CD%29&amp;tr=udp%3A%2F%2Ftracker.openbittorrent.com%3A80&amp;tr=udp%3A%2F%2Fopen.demonii.com%3A1337&amp;tr=udp%3A%2F%2Ftracker.coppersurfer.tk%3A6969&amp;tr=udp%3A%2F%2Fexodus.desync.com%3A6969","seeders":1,"leechers":0,"uploader":"nightissuchproximity","files":-1,"time":1254230247,"description":"CD 1 \n1 The Great Pretender - THE PLATTERS \n2 Bernadine - PAT BOONE \n3 Rock Around The Clock - BILL HALEY &amp; HIS COMETS \n4 Personality - LLOYD PRINCE \n5 Kisses Sweeter Than Wine - JIMMIE RODGERS \n6 Yakety Yak - THE COASTERS \n7 If You Ain't Lovin' - FARON YOUNG \n8 Kansas City - WILBERT HARRISON \n9 I'm In The Mood - JOHN LEE HOOKER \n10 Don't Forbit Me - PAT BOONE \n11 The Glow-Worm - THE MILLS BROTHERS \n12 Alley Oop - THE HOLLYWOOD ARGYLES \n13 Tom Dooley - THE KINGSTON TRIO \n14 Sleep Walk - SANTO &amp; JOHNNY \n15 Great Balls Of Fire - JERRY LEE LEWIS \n16 Sea Of Love - PHIL PHILLIPS &amp; THE TWILIGHTS \n17 Answer Me - FRANKIE LAINE \n18 At The Hop - DANNY &amp; THE JUNIORS \n\nCD 2 \n\n1 I'm Sorry - THE PLATTERS \n2 Blue Suede Shoes - CARL PERKINS \n3 Send Me The Pillow - HANK LOCKLIN \n4 Darling, Je Vous Aime Beaucoup - NAT KING COLE \n5 Raunchy - BILL JUSTIS \n6 Tequila - THE CHAMPS \n7 Charlie Brown - THE COASTERS \n8 Smoke Gets In Your Eyes - THE PLATTERS \n9 Tears On My Millow - LITTLE ANTHONY &amp; THE IMPERIALS \n10 There Goes My Baby - THE DRIFTERS \n11 Come Go With Me - THE DEL VIKINGS \n12 Reveille Rock - JOHNNY &amp; THE HURRICANES \n13 I Believe - FRANKIE LAINE \n14 Party Doll - BUDDY KNOX \n15 Be Bop A Lula - GENE VINCENT \n16 Rockin' Robin - BOBBY DAY \n17 Mack The Knife - LOUIS ARMSTRONG \n18 I Walk The Line - JOHNNY CASH \n\nCD 3 \n\n1 Whole Lotta Shakin' Goin' On - JERRY LEE LEWIS \n2 Lucille - LITTLE RICHARD \n3 Peggy Sue - BUDDY HOLLY &amp; THE PICKS \n4 See You Later Alligator - BILL HALEY &amp; HIS COMETS \n5 The Green Door - JIM LOWE \n6 Searchin' - THE COASTERS \n7 The Happy Organ - DAVE 'BABY' CORTEZ \n8 Ballad Of A Teenage Queen - JOHNNY CASH \n9 Walking After Midnight - PATSY CLINE \n10 Only You - THE PLATTERS \n11 Moonlight Serenade - GLENN MILLER \n12 Endless Sleep - JODY REYNOLDS \n13 April Love - PAT BOONE \n14 Why Do Fools Fall In Love - THE DIAMONDS \n15 Go Jimmy Go - JIMMY CLANTON \n16 Ooby Dooby - ROY ORBISON &amp; THE TEEN QUEENS \n17 Blueberry Hill - FATS DOMINO \n18 Rock And Roll Music - CHUCK BERRY\n\nmp3   CBR   192kbps\n\nall covers included","torrent":{"xt":"urn:btih:c09751b88d74b35c0a8ce99313d1d337f65e2298","amp;dn":"%28Various%29++Fabulous+Fifties+%283CD%29","amp;tr":["udp%3A%2F%2Ftracker.openbittorrent.com%3A80","udp%3A%2F%2Fopen.demonii.com%3A1337","udp%3A%2F%2Ftracker.coppersurfer.tk%3A6969","udp%3A%2F%2Fexodus.desync.com%3A6969"],"infoHash":"c09751b88d74b35c0a8ce99313d1d337f65e2298","infoHashBuffer":{"type":"Buffer","data":[192,151,81,184,141,116,179,92,10,140,233,147,19,209,211,55,246,94,34,152]},"announce":[],"urlList":[]}}