{"title":"Tecno remeber Sk Forever .mp3","uid":6262801,"size":95884478,"categoryP":"audio","categoryS":"music","magnet":"?xt=urn:btih:c743f551b6c16a7ee63d2150db7caeb2c183bcdb&amp;dn=Tecno+remeber+Sk+Forever+.mp3&amp;tr=udp%3A%2F%2Ftracker.openbittorrent.com%3A80&amp;tr=udp%3A%2F%2Fopen.demonii.com%3A1337&amp;tr=udp%3A%2F%2Ftracker.coppersurfer.tk%3A6969&amp;tr=udp%3A%2F%2Fexodus.desync.com%3A6969","seeders":1,"leechers":0,"uploader":"orkotroll","files":1,"time":1300803487,"description":"Mix de temas remebers, con mezclas algunas buenas y otras malas, pero con buenos temas, estan muchos de los esenciales que nos hicieron disfrutar en las pistas.\n\n\nMix remebers issues with mixing some good and some bad, but with good songs, are many of the essentials that made us enjoy the dance floors.\n\n\nAutor desconocido.","torrent":{"xt":"urn:btih:c743f551b6c16a7ee63d2150db7caeb2c183bcdb","amp;dn":"Tecno+remeber+Sk+Forever+.mp3","amp;tr":["udp%3A%2F%2Ftracker.openbittorrent.com%3A80","udp%3A%2F%2Fopen.demonii.com%3A1337","udp%3A%2F%2Ftracker.coppersurfer.tk%3A6969","udp%3A%2F%2Fexodus.desync.com%3A6969"],"infoHash":"c743f551b6c16a7ee63d2150db7caeb2c183bcdb","infoHashBuffer":{"type":"Buffer","data":[199,67,245,81,182,193,106,126,230,61,33,80,219,124,174,178,193,131,188,219]},"announce":[],"urlList":[]}}