{"title":"The.Tourist.2010.SWESUB.AC3.R5.XviD-BeNGT","uid":6134146,"size":1464504383,"categoryP":"video","categoryS":"movies","magnet":"?xt=urn:btih:cb876e7a164d70220a6f53e05f16f89d9f9cbcbf&amp;dn=The.Tourist.2010.SWESUB.AC3.R5.XviD-BeNGT&amp;tr=udp%3A%2F%2Ftracker.openbittorrent.com%3A80&amp;tr=udp%3A%2F%2Fopen.demonii.com%3A1337&amp;tr=udp%3A%2F%2Ftracker.coppersurfer.tk%3A6969&amp;tr=udp%3A%2F%2Fexodus.desync.com%3A6969","seeders":1,"leechers":0,"uploader":"DalarnaUberAlles","files":-1,"time":1296236381,"description":"Frank ÃƒÂ¤r en amerikansk turist som besÃƒÂ¶ker Italien fÃƒÂ¶r att kurera sitt brustna hjÃƒÂ¤rta. Elise ÃƒÂ¤r en extraordinÃƒÂ¤r tjej som avsiktligt korsar hans vÃƒÂ¤g. I de nervkittlande omgivningarna i Venedig inleder Frank en potentiell romans, men inser snart att bÃƒÂ¥de han och Elise har hamnat i en vÃƒÂ¥g av intriger och faror.\n\n\n\n\nRippad av BeNGT fÃƒÂ¶r dreamseed.nu\n\nTack iDiFF fÃƒÂ¶r undertexten.","torrent":{"xt":"urn:btih:cb876e7a164d70220a6f53e05f16f89d9f9cbcbf","amp;dn":"The.Tourist.2010.SWESUB.AC3.R5.XviD-BeNGT","amp;tr":["udp%3A%2F%2Ftracker.openbittorrent.com%3A80","udp%3A%2F%2Fopen.demonii.com%3A1337","udp%3A%2F%2Ftracker.coppersurfer.tk%3A6969","udp%3A%2F%2Fexodus.desync.com%3A6969"],"infoHash":"cb876e7a164d70220a6f53e05f16f89d9f9cbcbf","infoHashBuffer":{"type":"Buffer","data":[203,135,110,122,22,77,112,34,10,111,83,224,95,22,248,157,159,156,188,191]},"announce":[],"urlList":[]}}