{"title":"Edgar &amp; Johnny Winter (live 1990, 1993 )","uid":6256537,"size":160956731,"categoryP":"audio","categoryS":"music","magnet":"?xt=urn:btih:d088c6eb3002c7d87eb0fa3523c19320101f02fd&amp;dn=Edgar+%26+Johnny+Winter+%28live+1990%2C+1993+%29&amp;tr=udp%3A%2F%2Ftracker.openbittorrent.com%3A80&amp;tr=udp%3A%2F%2Fopen.demonii.com%3A1337&amp;tr=udp%3A%2F%2Ftracker.coppersurfer.tk%3A6969&amp;tr=udp%3A%2F%2Fexodus.desync.com%3A6969","seeders":1,"leechers":0,"uploader":"narpet","files":18,"time":1300597895,"description":"The albums/sets may not be complete.\nBe warned that some of the tracks are audience recorded and therefore low quality.\n\nThese were converted long ago, so there is a chance that a newer HiDef conversion has been pushed. (If so please post torrent link in comment, thanks)\n\n\nJohnnyWinter-live\n   Barcelona 051890 - Instrumental.MP3\n   Barcelona 051890 - Johnny B. Good.MP3\n   Barcelona 051890 - Serious as a Heart Attack.MP3\n   Barcelona 051890 - Stranger Blues.MP3\n   01_good_morning_little_school_girl.mp3\n   02_it's_my_own_fault.mp3\n   03_jumpin'_jack_flash.mp3\n   04_rock_and_roll_medley__great_balls_o.mp3\n   05_mean_town_blues.mp3\n   06_johnny_b__goode.mp3\n\nKingBiscuit_01-04-1993\n   01 edgar &amp; johnny winter intro.mp3\n   02 keep playin' that rack &amp; roll.mp3\n   03 frankenstein.mp3\n   04 tobacco road.mp3\n   05 free ride.mp3\n   06 bad luck situation.mp3\n   07 jumpin' jack flash.mp3\n   08 johnny b. goode.mp3\n","torrent":{"xt":"urn:btih:d088c6eb3002c7d87eb0fa3523c19320101f02fd","amp;dn":"Edgar+%26+Johnny+Winter+%28live+1990%2C+1993+%29","amp;tr":["udp%3A%2F%2Ftracker.openbittorrent.com%3A80","udp%3A%2F%2Fopen.demonii.com%3A1337","udp%3A%2F%2Ftracker.coppersurfer.tk%3A6969","udp%3A%2F%2Fexodus.desync.com%3A6969"],"infoHash":"d088c6eb3002c7d87eb0fa3523c19320101f02fd","infoHashBuffer":{"type":"Buffer","data":[208,136,198,235,48,2,199,216,126,176,250,53,35,193,147,32,16,31,2,253]},"announce":[],"urlList":[]}}