{"title":"CosÃƒÂ¬ come sei in English","uid":5046682,"size":373601318,"categoryP":"video","categoryS":"movies","magnet":"?xt=urn:btih:d6a4885d25dc6a8b5342513c2a76dd8149b27315&amp;dn=Cos%C3%83%C2%AC+come+sei+in+English&amp;tr=udp%3A%2F%2Ftracker.openbittorrent.com%3A80&amp;tr=udp%3A%2F%2Fopen.demonii.com%3A1337&amp;tr=udp%3A%2F%2Ftracker.coppersurfer.tk%3A6969&amp;tr=udp%3A%2F%2Fexodus.desync.com%3A6969","seeders":1,"leechers":0,"uploader":"gogo.86","files":2,"time":1249672366,"description":"Additional Details Released in 1978 in Italy\nAlso Known As:AsÃƒÂ­ como eres (Spain) \nStay as You Are (USA) \nStay the Way You Are \nParents Guide:Add content advisory for parents \nRuntime:\nFrance:105 min | Italy:109 min | West Germany:105 min | Argentina:110 min | USA:95 min \nCountry:Spain | Italy \nLanguage:Italian \nColor:Color \nSound Mix:\nMono Certification:\nArgentina:16 | Netherlands:16 | Finland:K-16 | USA:R \nCompany: P.C. Ales\n\nDescription\n\nI watched that movie in Italian and I hardly could ask for the way\n\nin that language. So I more or less had to guess the plot albeit it\n\nwas not too much of an effort given the complexity of it ;)\n\n17 years old female (Nastassja Kinski) falls in love with a 50 years\n\nold who could be her father. Eventually he turns out to indeed be her\n\nfather. To me the all time most graceful and beautiful (insert all other\n\nthinkable positive attributes appropriate for describing a goddess\n\nhere) picture of a female appearance was in that scene when he was\n\nwatering some plants in his house and then she came in smilingly saying\n\nCiao.","torrent":{"xt":"urn:btih:d6a4885d25dc6a8b5342513c2a76dd8149b27315","amp;dn":"Cos%C3%83%C2%AC+come+sei+in+English","amp;tr":["udp%3A%2F%2Ftracker.openbittorrent.com%3A80","udp%3A%2F%2Fopen.demonii.com%3A1337","udp%3A%2F%2Ftracker.coppersurfer.tk%3A6969","udp%3A%2F%2Fexodus.desync.com%3A6969"],"infoHash":"d6a4885d25dc6a8b5342513c2a76dd8149b27315","infoHashBuffer":{"type":"Buffer","data":[214,164,136,93,37,220,106,139,83,66,81,60,42,118,221,129,73,178,115,21]},"announce":[],"urlList":[]}}