{"title":"DIE ZEIT 2011 09","uid":6198974,"size":15629151,"categoryP":"other","categoryS":"e_books","magnet":"?xt=urn:btih:f08afaada496e96871180b8b16899bb743e4159b&amp;dn=DIE+ZEIT+2011+09&amp;tr=udp%3A%2F%2Ftracker.openbittorrent.com%3A80&amp;tr=udp%3A%2F%2Fopen.demonii.com%3A1337&amp;tr=udp%3A%2F%2Ftracker.coppersurfer.tk%3A6969&amp;tr=udp%3A%2F%2Fexodus.desync.com%3A6969","seeders":1,"leechers":0,"uploader":"papiertiger","files":-1,"time":1298541674,"description":"Ausgabe 09/2011 der Wochenzeitung &quot;DIE ZEIT&quot; (PDF &amp; ePub)","torrent":{"xt":"urn:btih:f08afaada496e96871180b8b16899bb743e4159b","amp;dn":"DIE+ZEIT+2011+09","amp;tr":["udp%3A%2F%2Ftracker.openbittorrent.com%3A80","udp%3A%2F%2Fopen.demonii.com%3A1337","udp%3A%2F%2Ftracker.coppersurfer.tk%3A6969","udp%3A%2F%2Fexodus.desync.com%3A6969"],"infoHash":"f08afaada496e96871180b8b16899bb743e4159b","infoHashBuffer":{"type":"Buffer","data":[240,138,250,173,164,150,233,104,113,24,11,139,22,137,155,183,67,228,21,155]},"announce":[],"urlList":[]}}