{"title":"Bionicle The Legend Reborn (2009) NTSC (nl subs)  2Lion-Team","uid":5096134,"size":4030025420,"categoryP":"video","categoryS":"movies_dvdr","magnet":"?xt=urn:btih:f568c17d4242fad220b8e38d0a39eb94d6deedd2&amp;dn=Bionicle+The+Legend+Reborn+%282009%29+NTSC+%28nl+subs%29++2Lion-Team&amp;tr=udp%3A%2F%2Ftracker.openbittorrent.com%3A80&amp;tr=udp%3A%2F%2Fopen.demonii.com%3A1337&amp;tr=udp%3A%2F%2Ftracker.coppersurfer.tk%3A6969&amp;tr=udp%3A%2F%2Fexodus.desync.com%3A6969","seeders":1,"leechers":0,"uploader":null,"files":-1,"time":1253583358,"description":"Bionicle The Legend Reborn (2009) NTSC       \n\n \n  Bionicle The Legend Reborn 2009 NTSC DVDR-JKR \n\n\n\nVerenigde Staten\nAnimatie / Actie\n80 minuten\n\ngeregisseerd door Mark Baldo\nmet de stemmen van Jeff Bennett, Jim Cummings en Michael Dorn\n\nMata Nui, ooit een groot en machtig heerser, \nwerd verbannen naar een afgelegen woestenij vol schroot en glinsterende metalen. \nNadat hij als overwinnaar uit een gevaarlijke strijd is gekomen, roepen de plaatselijke dorpsbewoners zijn hulp in voor de strijd tegen hun echte vijanden: \nde kwaadaardige Skrall en de Bone Hunters. \nSamen met zijn moedige Glatoriaanse krijgers en de dorpelingen van Agori, \nvertrekt Mata Nui op een epische avonturentocht die hem naar fantastische nieuwe landen voert.\n\n**************\n\nEnglish\n\nOnce the ruler of an entire universe, the Great Spirit Mata Nui finds himself cast out of his own body, his spirit trapped inside the fabled Mask of Life, hurtling through space. After landing on the far-away planet of Bara Magna, the mask creates a new body for Mata Nui, who unwillingly gets caught up in the furious battles of the nearly barren and dangerous planet. The locals, called Agori ask for his help against the unrelenting army of the Rock Tribe, called the Skrall and their leader, Tuma. The Glatorian warriors start to train him, teach him how to protect himself, while Mata Nui also adds some of his special powers to their fighting skill. The experienced veteran Ackar, the feisty female Kiina, the young Glatorian Gresh, and a friendly, special beetle named Click aid him on his way. But there is a traitor among the Agori, and bigger secrets lay hidden under the sands of the desert planet. Mata Nui must help his new-found friends, but he also has to find a way to return to his old body and take revenge on the evil being who had banished him\n\n**************\nSOURCE : R1 NTSC\nMENUS : YES\nLANGUAGE : 5.1 DD English, \nSUBTiTLES : Nederlands door Gonnie en Martien\nControle: Gonnie\nBewerking: Send\nEXTRAS : All\nSTRiPPED : Beginning junk, French &amp; Spanish audio\nBITRATE : 6 pass cce @ 5797Kbps\n\nSpotinformatie \nCategorie : Beeld \nFormaat : DVD5 \nBron : Retail\n \nOndertitels : Nederland (instelbaar)\n \nGenre : Actie\nAvontuur\nAnimatie\nScience Fiction\n \n\nWeblink : &lt;a href=&quot; http://www.moviemeter.nl/film/59670&quot; rel=&quot;nofollow&quot; target=&quot;_NEW&quot;&gt; http://www.moviemeter.nl/film/59670&lt;/a&gt; \nWeblink : &lt;a href=&quot; http://www.imdb.com/title/tt1473345&quot; rel=&quot;nofollow&quot; target=&quot;_NEW&quot;&gt; http://www.imdb.com/title/tt1473345&lt;/a&gt;\n\n","torrent":{"xt":"urn:btih:f568c17d4242fad220b8e38d0a39eb94d6deedd2","amp;dn":"Bionicle+The+Legend+Reborn+%282009%29+NTSC+%28nl+subs%29++2Lion-Team","amp;tr":["udp%3A%2F%2Ftracker.openbittorrent.com%3A80","udp%3A%2F%2Fopen.demonii.com%3A1337","udp%3A%2F%2Ftracker.coppersurfer.tk%3A6969","udp%3A%2F%2Fexodus.desync.com%3A6969"],"infoHash":"f568c17d4242fad220b8e38d0a39eb94d6deedd2","infoHashBuffer":{"type":"Buffer","data":[245,104,193,125,66,66,250,210,32,184,227,141,10,57,235,148,214,222,237,210]},"announce":[],"urlList":[]}}